gufo/liftbridge/__init__.py
gufo/liftbridge/api_pb2.py
gufo/liftbridge/api_pb2.pyi
gufo/liftbridge/api_pb2_grpc.py
gufo/liftbridge/client.py
gufo/liftbridge/compressor.py
gufo/liftbridge/error.py
gufo/liftbridge/liftbridge.py
gufo/liftbridge/py.typed
gufo/liftbridge/types.py
gufo/liftbridge/utils.py
gufo_liftbridge-0.2.0.dist-info/licenses/LICENSE.md
gufo_liftbridge-0.2.0.dist-info/METADATA
gufo_liftbridge-0.2.0.dist-info/WHEEL
gufo_liftbridge-0.2.0.dist-info/top_level.txt
gufo_liftbridge-0.2.0.dist-info/RECORD
