Metadata-Version: 2.4
Name: gufo_liftbridge
Version: 0.2.0
Summary: An asynchronous Python Liftbridge client
Author: Gufo Labs
License: BSD 3-Clause License
Project-URL: Bug Tracker, https://github.com/gufolabs/gufo_liftbridge/issues
Project-URL: Changelog, https://github.com/gufolabs/gufo_liftbridge/blob/master/CHANGELOG.md
Project-URL: Documentation, https://docs.gufolabs.com/gufo_liftbridge/
Project-URL: Homepage, https://github.com/gufolabs/gufo_liftbridge/
Project-URL: Source Code, https://github.com/gufolabs/gufo_liftbridge/
Keywords: error
Classifier: Development Status :: 5 - Production/Stable
Classifier: Intended Audience :: Developers
Classifier: Programming Language :: Python :: 3.9
Classifier: Programming Language :: Python :: 3.10
Classifier: Programming Language :: Python :: 3.11
Classifier: Programming Language :: Python :: 3.12
Classifier: Programming Language :: Python :: 3.13
Classifier: License :: OSI Approved :: BSD License
Classifier: Topic :: Software Development
Classifier: Topic :: Software Development :: Libraries
Classifier: Topic :: Software Development :: Libraries :: Python Modules
Classifier: Operating System :: OS Independent
Classifier: Typing :: Typed
Requires-Python: >=3.9
License-File: LICENSE.md
Requires-Dist: grpcio>=1.74.0
Requires-Dist: types-protobuf>=6.30
Requires-Dist: protobuf>=6.32
Provides-Extra: dev
Requires-Dist: grpcio-tools>=1.74.0; extra == "dev"
Provides-Extra: docs
Requires-Dist: mkdocs-material==9.5.44; extra == "docs"
Requires-Dist: mkdocstrings[python]==0.27.0; extra == "docs"
Requires-Dist: mkdocs-gen-files==0.5.0; extra == "docs"
Requires-Dist: mkdocs-literate-nav==0.6.1; extra == "docs"
Requires-Dist: mkdocs-section-index==0.3.9; extra == "docs"
Provides-Extra: ipython
Requires-Dist: ipython==9.4.0; extra == "ipython"
Provides-Extra: lint
Requires-Dist: mypy==1.13.0; extra == "lint"
Requires-Dist: ruff==0.11.2; extra == "lint"
Requires-Dist: types-PyYAML==6.0.12.3; extra == "lint"
Provides-Extra: test
Requires-Dist: pytest==8.3.3; extra == "test"
Requires-Dist: coverage[toml]==7.6.4; extra == "test"
Requires-Dist: PyYAML>=6.0; extra == "test"
Dynamic: license-file
